pe_oudin/PE_Oudin.py
pe_oudin/__init__.py
pe_oudin/test_pe_oudin.py
PE_Oudin-0.3.dist-info/LICENSE
PE_Oudin-0.3.dist-info/METADATA
PE_Oudin-0.3.dist-info/WHEEL
PE_Oudin-0.3.dist-info/top_level.txt
PE_Oudin-0.3.dist-info/RECORD
