Metadata-Version: 2.1
Name: PE-Oudin
Version: 0.3
Summary: Calculate potential evapotranspiration from temperature
Home-page: https://gitlab.com/pazdror/potEvap
Author: Dror Paz
Author-email: pazdror@gmail.com
License: UNKNOWN
Platform: UNKNOWN
Classifier: Programming Language :: Python :: 3
Classifier: Operating System :: OS Independent
Classifier: Development Status :: 4 - Beta
Classifier: Intended Audience :: Science/Research
Classifier: License :: OSI Approved :: GNU General Public License v2 (GPLv2)
Classifier: Topic :: Scientific/Engineering :: Atmospheric Science
Requires-Python: >=3.6
